caps/__init__.py
caps/admin.py
caps/apps.py
caps/backends.py
caps/forms.py
caps/locale/de/LC_MESSAGES/django.po
caps/locale/es/LC_MESSAGES/django.po
caps/locale/fr/LC_MESSAGES/django.po
caps/locale/nl/LC_MESSAGES/django.po
caps/middleware.py
caps/migrations/0001_initial.py
caps/migrations/__init__.py
caps/models/__init__.py
caps/models/access.py
caps/models/agent.py
caps/models/nested.py
caps/models/owned.py
caps/permissions.py
caps/serializers.py
caps/signals.py
caps/urls.py
caps/utils/__init__.py
caps/utils/nested.py
caps/views/__init__.py
caps/views/api.py
caps/views/common.py
caps/views/generics.py
caps/views/mixins.py
django_caps-0.0.3.dist-info/METADATA
django_caps-0.0.3.dist-info/WHEEL
django_caps-0.0.3.dist-info/licenses/LICENSE
django_caps-0.0.3.dist-info/RECORD
