Metadata-Version: 2.4
Name: django-caps
Version: 0.0.3
Summary: Capability based object permissions for Django.
License: MPL-2.0
License-File: LICENSE
Author: Thomas Baquet
Author-email: thomas@oxylus.app
Requires-Python: >=3.13,<4.0
Classifier: Framework :: Django
Classifier: Framework :: Django :: 5.0
Classifier: Intended Audience :: Developers
Classifier: License :: OSI Approved
Classifier: License :: OSI Approved :: Mozilla Public License 2.0 (MPL 2.0)
Classifier: Programming Language :: Python
Classifier: Programming Language :: Python :: 3
Classifier: Programming Language :: Python :: 3.13
Classifier: Programming Language :: Python :: 3.14
Classifier: Programming Language :: Python :: 3.11
Classifier: Topic :: Security
Classifier: Topic :: Software Development :: Libraries
Classifier: Topic :: Software Development :: Libraries :: Python Modules
Classifier: Topic :: Software Development :: Object Brokering
Requires-Dist: Django (>=5,<6)
Requires-Dist: django-filter (>=25.2,<26.0)
Requires-Dist: djangorestframework (>=3,<4)
